{
    "pages": [
        {
            "name": "New",
            "icon": "/assets/icons/plus.svg",
            "section": "new"
        }, 
        {
            "name": "Tasks",
            "icon": "/assets/icons/checklist.svg",
            "section": "tasks"
        },
        {
            "name": "Focus",
            "icon": "/assets/icons/house.svg",
            "section": "focus"
        },
        {
            "name": "Routine",
            "icon": "/assets/icons/clock.svg",
            "section": "routine"
        },
        {
            "name": "Settings",
            "icon": "/assets/icons/gear.svg",
            "section": "settings"
        }
    ]
}